[
    {
        "fixture": {
            "id": 1528334,
            "referee": null,
            "timezone": "America/New_York",
            "date": "2026-03-12T13:45:00-04:00",
            "timestamp": 1773337500,
            "periods": {
                "first": null,
                "second": null
            },
            "venue": {
                "id": null,
                "name": "Stade Pierre-Mauroy",
                "city": null
            },
            "status": {
                "long": "Not Started",
                "short": "NS",
                "elapsed": null,
                "extra": null
            }
        },
        "league": {
            "id": 3,
            "name": "UEFA Europa League",
            "country": "World",
            "logo": "https://media.api-sports.io/football/leagues/3.png",
            "flag": null,
            "season": 2025,
            "round": "Round of 16",
            "standings": true
        },
        "teams": {
            "home": {
                "id": 79,
                "name": "Lille",
                "logo": "https://media.api-sports.io/football/teams/79.png",
                "winner": null,
                "rank": null,
                "record": null
            },
            "away": {
                "id": 66,
                "name": "Aston Villa",
                "logo": "https://media.api-sports.io/football/teams/66.png",
                "winner": null,
                "rank": null,
                "record": null
            }
        },
        "goals": {
            "home": null,
            "away": null
        },
        "homeLineup": null,
        "awayLineup": null,
        "odds": {
            "home": "TBD",
            "draw": "TBD",
            "away": "TBD",
            "total": "TBD",
            "over": "TBD",
            "under": "TBD"
        },
        "last_odds_check": null,
        "injuries": {
            "home": [],
            "away": [],
            "fetched": false
        },
        "events": []
    },
    {
        "fixture": {
            "id": 1528335,
            "referee": null,
            "timezone": "America/New_York",
            "date": "2026-03-12T13:45:00-04:00",
            "timestamp": 1773337500,
            "periods": {
                "first": null,
                "second": null
            },
            "venue": {
                "id": 0,
                "name": null,
                "city": "Bologna"
            },
            "status": {
                "long": "Not Started",
                "short": "NS",
                "elapsed": null,
                "extra": null
            }
        },
        "league": {
            "id": 3,
            "name": "UEFA Europa League",
            "country": "World",
            "logo": "https://media.api-sports.io/football/leagues/3.png",
            "flag": null,
            "season": 2025,
            "round": "Round of 16",
            "standings": true
        },
        "teams": {
            "home": {
                "id": 500,
                "name": "Bologna",
                "logo": "https://media.api-sports.io/football/teams/500.png",
                "winner": null,
                "rank": null,
                "record": null
            },
            "away": {
                "id": 497,
                "name": "AS Roma",
                "logo": "https://media.api-sports.io/football/teams/497.png",
                "winner": null,
                "rank": null,
                "record": null
            }
        },
        "goals": {
            "home": null,
            "away": null
        },
        "homeLineup": null,
        "awayLineup": null,
        "odds": {
            "home": "TBD",
            "draw": "TBD",
            "away": "TBD",
            "total": "TBD",
            "over": "TBD",
            "under": "TBD"
        },
        "last_odds_check": null,
        "injuries": {
            "home": [],
            "away": [],
            "fetched": false
        },
        "events": []
    },
    {
        "fixture": {
            "id": 1528336,
            "referee": null,
            "timezone": "America/New_York",
            "date": "2026-03-12T13:45:00-04:00",
            "timestamp": 1773337500,
            "periods": {
                "first": null,
                "second": null
            },
            "venue": {
                "id": null,
                "name": "MHPArena",
                "city": "Stuttgart"
            },
            "status": {
                "long": "Not Started",
                "short": "NS",
                "elapsed": null,
                "extra": null
            }
        },
        "league": {
            "id": 3,
            "name": "UEFA Europa League",
            "country": "World",
            "logo": "https://media.api-sports.io/football/leagues/3.png",
            "flag": null,
            "season": 2025,
            "round": "Round of 16",
            "standings": true
        },
        "teams": {
            "home": {
                "id": 172,
                "name": "VfB Stuttgart",
                "logo": "https://media.api-sports.io/football/teams/172.png",
                "winner": null,
                "rank": null,
                "record": null
            },
            "away": {
                "id": 212,
                "name": "FC Porto",
                "logo": "https://media.api-sports.io/football/teams/212.png",
                "winner": null,
                "rank": null,
                "record": null
            }
        },
        "goals": {
            "home": null,
            "away": null
        },
        "homeLineup": null,
        "awayLineup": null,
        "odds": {
            "home": "TBD",
            "draw": "TBD",
            "away": "TBD",
            "total": "TBD",
            "over": "TBD",
            "under": "TBD"
        },
        "last_odds_check": null,
        "injuries": {
            "home": [],
            "away": [],
            "fetched": false
        },
        "events": []
    },
    {
        "fixture": {
            "id": 1528337,
            "referee": null,
            "timezone": "America/New_York",
            "date": "2026-03-12T13:45:00-04:00",
            "timestamp": 1773337500,
            "periods": {
                "first": null,
                "second": null
            },
            "venue": {
                "id": null,
                "name": "Olympic Stadium of Athens",
                "city": "Athens"
            },
            "status": {
                "long": "Not Started",
                "short": "NS",
                "elapsed": null,
                "extra": null
            }
        },
        "league": {
            "id": 3,
            "name": "UEFA Europa League",
            "country": "World",
            "logo": "https://media.api-sports.io/football/leagues/3.png",
            "flag": null,
            "season": 2025,
            "round": "Round of 16",
            "standings": true
        },
        "teams": {
            "home": {
                "id": 617,
                "name": "Panathinaikos",
                "logo": "https://media.api-sports.io/football/teams/617.png",
                "winner": null,
                "rank": null,
                "record": null
            },
            "away": {
                "id": 543,
                "name": "Real Betis",
                "logo": "https://media.api-sports.io/football/teams/543.png",
                "winner": null,
                "rank": null,
                "record": null
            }
        },
        "goals": {
            "home": null,
            "away": null
        },
        "homeLineup": null,
        "awayLineup": null,
        "odds": {
            "home": "TBD",
            "draw": "TBD",
            "away": "TBD",
            "total": "TBD",
            "over": "TBD",
            "under": "TBD"
        },
        "last_odds_check": null,
        "injuries": {
            "home": [],
            "away": [],
            "fetched": false
        },
        "events": []
    },
    {
        "fixture": {
            "id": 1436139,
            "referee": null,
            "timezone": "America/New_York",
            "date": "2026-03-12T15:00:00-04:00",
            "timestamp": 1773342000,
            "periods": {
                "first": null,
                "second": null
            },
            "venue": {
                "id": null,
                "name": "Al-Hazem Club Stadium",
                "city": "Ar Rass"
            },
            "status": {
                "long": "Not Started",
                "short": "NS",
                "elapsed": null,
                "extra": null
            }
        },
        "league": {
            "id": 307,
            "name": "Pro League",
            "country": "Saudi-Arabia",
            "logo": "https://media.api-sports.io/football/leagues/307.png",
            "flag": "https://media.api-sports.io/flags/sa.svg",
            "season": 2025,
            "round": "Regular Season - 26",
            "standings": true
        },
        "teams": {
            "home": {
                "id": 2945,
                "name": "Al-Hazm",
                "logo": "https://media.api-sports.io/football/teams/2945.png",
                "winner": null,
                "rank": null,
                "record": null
            },
            "away": {
                "id": 10509,
                "name": "Al Kholood",
                "logo": "https://media.api-sports.io/football/teams/10509.png",
                "winner": null,
                "rank": null,
                "record": null
            }
        },
        "goals": {
            "home": null,
            "away": null
        },
        "homeLineup": null,
        "awayLineup": null,
        "odds": {
            "home": "TBD",
            "draw": "TBD",
            "away": "TBD",
            "total": "TBD",
            "over": "TBD",
            "under": "TBD"
        },
        "last_odds_check": null,
        "injuries": {
            "home": [],
            "away": [],
            "fetched": false
        },
        "events": []
    },
    {
        "fixture": {
            "id": 1436140,
            "referee": null,
            "timezone": "America/New_York",
            "date": "2026-03-12T15:00:00-04:00",
            "timestamp": 1773342000,
            "periods": {
                "first": null,
                "second": null
            },
            "venue": {
                "id": null,
                "name": "King Abdullah Sports City Stadium",
                "city": "Buraidah"
            },
            "status": {
                "long": "Not Started",
                "short": "NS",
                "elapsed": null,
                "extra": null
            }
        },
        "league": {
            "id": 307,
            "name": "Pro League",
            "country": "Saudi-Arabia",
            "logo": "https://media.api-sports.io/football/leagues/307.png",
            "flag": "https://media.api-sports.io/flags/sa.svg",
            "season": 2025,
            "round": "Regular Season - 26",
            "standings": true
        },
        "teams": {
            "home": {
                "id": 2992,
                "name": "Al Najma",
                "logo": "https://media.api-sports.io/football/teams/2992.png",
                "winner": null,
                "rank": null,
                "record": null
            },
            "away": {
                "id": 2956,
                "name": "Damac",
                "logo": "https://media.api-sports.io/football/teams/2956.png",
                "winner": null,
                "rank": null,
                "record": null
            }
        },
        "goals": {
            "home": null,
            "away": null
        },
        "homeLineup": null,
        "awayLineup": null,
        "odds": {
            "home": "TBD",
            "draw": "TBD",
            "away": "TBD",
            "total": "TBD",
            "over": "TBD",
            "under": "TBD"
        },
        "last_odds_check": null,
        "injuries": {
            "home": [],
            "away": [],
            "fetched": false
        },
        "events": []
    },
    {
        "fixture": {
            "id": 1436145,
            "referee": null,
            "timezone": "America/New_York",
            "date": "2026-03-12T15:00:00-04:00",
            "timestamp": 1773342000,
            "periods": {
                "first": null,
                "second": null
            },
            "venue": {
                "id": null,
                "name": "King Khalid Sports City",
                "city": "Tabuk"
            },
            "status": {
                "long": "Not Started",
                "short": "NS",
                "elapsed": null,
                "extra": null
            }
        },
        "league": {
            "id": 307,
            "name": "Pro League",
            "country": "Saudi-Arabia",
            "logo": "https://media.api-sports.io/football/leagues/307.png",
            "flag": "https://media.api-sports.io/flags/sa.svg",
            "season": 2025,
            "round": "Regular Season - 26",
            "standings": true
        },
        "teams": {
            "home": {
                "id": 10513,
                "name": "NEOM",
                "logo": "https://media.api-sports.io/football/teams/10513.png",
                "winner": null,
                "rank": null,
                "record": null
            },
            "away": {
                "id": 2936,
                "name": "Al Taawon",
                "logo": "https://media.api-sports.io/football/teams/2936.png",
                "winner": null,
                "rank": null,
                "record": null
            }
        },
        "goals": {
            "home": null,
            "away": null
        },
        "homeLineup": null,
        "awayLineup": null,
        "odds": {
            "home": "TBD",
            "draw": "TBD",
            "away": "TBD",
            "total": "TBD",
            "over": "TBD",
            "under": "TBD"
        },
        "last_odds_check": null,
        "injuries": {
            "home": [],
            "away": [],
            "fetched": false
        },
        "events": []
    },
    {
        "fixture": {
            "id": 1491957,
            "referee": null,
            "timezone": "America/New_York",
            "date": "2026-03-12T16:00:00-04:00",
            "timestamp": 1773345600,
            "periods": {
                "first": null,
                "second": null
            },
            "venue": {
                "id": null,
                "name": "Estadio Norberto Tito Tomaghello",
                "city": "Gobernador Julio A. Costa"
            },
            "status": {
                "long": "Not Started",
                "short": "NS",
                "elapsed": null,
                "extra": null
            }
        },
        "league": {
            "id": 128,
            "name": "Liga Profesional Argentina",
            "country": "Argentina",
            "logo": "https://media.api-sports.io/football/leagues/128.png",
            "flag": "https://media.api-sports.io/flags/ar.svg",
            "season": 2026,
            "round": "Regular Season - 10",
            "standings": true
        },
        "teams": {
            "home": {
                "id": 442,
                "name": "Defensa Y Justicia",
                "logo": "https://media.api-sports.io/football/teams/442.png",
                "winner": null,
                "rank": null,
                "record": null
            },
            "away": {
                "id": 1065,
                "name": "Central Cordoba de Santiago",
                "logo": "https://media.api-sports.io/football/teams/1065.png",
                "winner": null,
                "rank": null,
                "record": null
            }
        },
        "goals": {
            "home": null,
            "away": null
        },
        "homeLineup": null,
        "awayLineup": null,
        "odds": {
            "home": "TBD",
            "draw": "TBD",
            "away": "TBD",
            "total": "TBD",
            "over": "TBD",
            "under": "TBD"
        },
        "last_odds_check": null,
        "injuries": {
            "home": [],
            "away": [],
            "fetched": false
        },
        "events": []
    },
    {
        "fixture": {
            "id": 1491958,
            "referee": null,
            "timezone": "America/New_York",
            "date": "2026-03-12T16:00:00-04:00",
            "timestamp": 1773345600,
            "periods": {
                "first": null,
                "second": null
            },
            "venue": {
                "id": null,
                "name": "Estadio Guillermo Laza",
                "city": "Buenos Aires"
            },
            "status": {
                "long": "Not Started",
                "short": "NS",
                "elapsed": null,
                "extra": null
            }
        },
        "league": {
            "id": 128,
            "name": "Liga Profesional Argentina",
            "country": "Argentina",
            "logo": "https://media.api-sports.io/football/leagues/128.png",
            "flag": "https://media.api-sports.io/flags/ar.svg",
            "season": 2026,
            "round": "Regular Season - 10",
            "standings": true
        },
        "teams": {
            "home": {
                "id": 476,
                "name": "Deportivo Riestra",
                "logo": "https://media.api-sports.io/football/teams/476.png",
                "winner": null,
                "rank": null,
                "record": null
            },
            "away": {
                "id": 1066,
                "name": "Gimnasia M.",
                "logo": "https://media.api-sports.io/football/teams/1066.png",
                "winner": null,
                "rank": null,
                "record": null
            }
        },
        "goals": {
            "home": null,
            "away": null
        },
        "homeLineup": null,
        "awayLineup": null,
        "odds": {
            "home": "TBD",
            "draw": "TBD",
            "away": "TBD",
            "total": "TBD",
            "over": "TBD",
            "under": "TBD"
        },
        "last_odds_check": null,
        "injuries": {
            "home": [],
            "away": [],
            "fetched": false
        },
        "events": []
    },
    {
        "fixture": {
            "id": 1528338,
            "referee": null,
            "timezone": "America/New_York",
            "date": "2026-03-12T16:00:00-04:00",
            "timestamp": 1773345600,
            "periods": {
                "first": null,
                "second": null
            },
            "venue": {
                "id": 0,
                "name": null,
                "city": "Vigo"
            },
            "status": {
                "long": "Not Started",
                "short": "NS",
                "elapsed": null,
                "extra": null
            }
        },
        "league": {
            "id": 3,
            "name": "UEFA Europa League",
            "country": "World",
            "logo": "https://media.api-sports.io/football/leagues/3.png",
            "flag": null,
            "season": 2025,
            "round": "Round of 16",
            "standings": true
        },
        "teams": {
            "home": {
                "id": 538,
                "name": "Celta Vigo",
                "logo": "https://media.api-sports.io/football/teams/538.png",
                "winner": null,
                "rank": null,
                "record": null
            },
            "away": {
                "id": 80,
                "name": "Lyon",
                "logo": "https://media.api-sports.io/football/teams/80.png",
                "winner": null,
                "rank": null,
                "record": null
            }
        },
        "goals": {
            "home": null,
            "away": null
        },
        "homeLineup": null,
        "awayLineup": null,
        "odds": {
            "home": "TBD",
            "draw": "TBD",
            "away": "TBD",
            "total": "TBD",
            "over": "TBD",
            "under": "TBD"
        },
        "last_odds_check": null,
        "injuries": {
            "home": [],
            "away": [],
            "fetched": false
        },
        "events": []
    },
    {
        "fixture": {
            "id": 1528339,
            "referee": null,
            "timezone": "America/New_York",
            "date": "2026-03-12T16:00:00-04:00",
            "timestamp": 1773345600,
            "periods": {
                "first": null,
                "second": null
            },
            "venue": {
                "id": null,
                "name": "City Ground",
                "city": "Nottingham"
            },
            "status": {
                "long": "Not Started",
                "short": "NS",
                "elapsed": null,
                "extra": null
            }
        },
        "league": {
            "id": 3,
            "name": "UEFA Europa League",
            "country": "World",
            "logo": "https://media.api-sports.io/football/leagues/3.png",
            "flag": null,
            "season": 2025,
            "round": "Round of 16",
            "standings": true
        },
        "teams": {
            "home": {
                "id": 65,
                "name": "Nottingham Forest",
                "logo": "https://media.api-sports.io/football/teams/65.png",
                "winner": null,
                "rank": null,
                "record": null
            },
            "away": {
                "id": 397,
                "name": "FC Midtjylland",
                "logo": "https://media.api-sports.io/football/teams/397.png",
                "winner": null,
                "rank": null,
                "record": null
            }
        },
        "goals": {
            "home": null,
            "away": null
        },
        "homeLineup": null,
        "awayLineup": null,
        "odds": {
            "home": "TBD",
            "draw": "TBD",
            "away": "TBD",
            "total": "TBD",
            "over": "TBD",
            "under": "TBD"
        },
        "last_odds_check": null,
        "injuries": {
            "home": [],
            "away": [],
            "fetched": false
        },
        "events": []
    },
    {
        "fixture": {
            "id": 1528340,
            "referee": null,
            "timezone": "America/New_York",
            "date": "2026-03-12T16:00:00-04:00",
            "timestamp": 1773345600,
            "periods": {
                "first": null,
                "second": null
            },
            "venue": {
                "id": null,
                "name": "Groupama Arena",
                "city": "Budapest"
            },
            "status": {
                "long": "Not Started",
                "short": "NS",
                "elapsed": null,
                "extra": null
            }
        },
        "league": {
            "id": 3,
            "name": "UEFA Europa League",
            "country": "World",
            "logo": "https://media.api-sports.io/football/leagues/3.png",
            "flag": null,
            "season": 2025,
            "round": "Round of 16",
            "standings": true
        },
        "teams": {
            "home": {
                "id": 651,
                "name": "Ferencvarosi TC",
                "logo": "https://media.api-sports.io/football/teams/651.png",
                "winner": null,
                "rank": null,
                "record": null
            },
            "away": {
                "id": 217,
                "name": "SC Braga",
                "logo": "https://media.api-sports.io/football/teams/217.png",
                "winner": null,
                "rank": null,
                "record": null
            }
        },
        "goals": {
            "home": null,
            "away": null
        },
        "homeLineup": null,
        "awayLineup": null,
        "odds": {
            "home": "TBD",
            "draw": "TBD",
            "away": "TBD",
            "total": "TBD",
            "over": "TBD",
            "under": "TBD"
        },
        "last_odds_check": null,
        "injuries": {
            "home": [],
            "away": [],
            "fetched": false
        },
        "events": []
    },
    {
        "fixture": {
            "id": 1528341,
            "referee": null,
            "timezone": "America/New_York",
            "date": "2026-03-12T16:00:00-04:00",
            "timestamp": 1773345600,
            "periods": {
                "first": null,
                "second": null
            },
            "venue": {
                "id": null,
                "name": "Cegeka Arena",
                "city": "Genk"
            },
            "status": {
                "long": "Not Started",
                "short": "NS",
                "elapsed": null,
                "extra": null
            }
        },
        "league": {
            "id": 3,
            "name": "UEFA Europa League",
            "country": "World",
            "logo": "https://media.api-sports.io/football/leagues/3.png",
            "flag": null,
            "season": 2025,
            "round": "Round of 16",
            "standings": true
        },
        "teams": {
            "home": {
                "id": 742,
                "name": "Genk",
                "logo": "https://media.api-sports.io/football/teams/742.png",
                "winner": null,
                "rank": null,
                "record": null
            },
            "away": {
                "id": 160,
                "name": "SC Freiburg",
                "logo": "https://media.api-sports.io/football/teams/160.png",
                "winner": null,
                "rank": null,
                "record": null
            }
        },
        "goals": {
            "home": null,
            "away": null
        },
        "homeLineup": null,
        "awayLineup": null,
        "odds": {
            "home": "TBD",
            "draw": "TBD",
            "away": "TBD",
            "total": "TBD",
            "over": "TBD",
            "under": "TBD"
        },
        "last_odds_check": null,
        "injuries": {
            "home": [],
            "away": [],
            "fetched": false
        },
        "events": []
    },
    {
        "fixture": {
            "id": 1492157,
            "referee": null,
            "timezone": "America/New_York",
            "date": "2026-03-12T18:00:00-04:00",
            "timestamp": 1773352800,
            "periods": {
                "first": null,
                "second": null
            },
            "venue": {
                "id": null,
                "name": "Estadio Evandro Almeida",
                "city": "Belem"
            },
            "status": {
                "long": "Not Started",
                "short": "NS",
                "elapsed": null,
                "extra": null
            }
        },
        "league": {
            "id": 71,
            "name": "Serie A",
            "country": "Brazil",
            "logo": "https://media.api-sports.io/football/leagues/71.png",
            "flag": "https://media.api-sports.io/flags/br.svg",
            "season": 2026,
            "round": "Regular Season - 5",
            "standings": true
        },
        "teams": {
            "home": {
                "id": 1198,
                "name": "remo",
                "logo": "https://media.api-sports.io/football/teams/1198.png",
                "winner": null,
                "rank": null,
                "record": null
            },
            "away": {
                "id": 124,
                "name": "Fluminense",
                "logo": "https://media.api-sports.io/football/teams/124.png",
                "winner": null,
                "rank": null,
                "record": null
            }
        },
        "goals": {
            "home": null,
            "away": null
        },
        "homeLineup": null,
        "awayLineup": null,
        "odds": {
            "home": "TBD",
            "draw": "TBD",
            "away": "TBD",
            "total": "TBD",
            "over": "TBD",
            "under": "TBD"
        },
        "last_odds_check": null,
        "injuries": {
            "home": [],
            "away": [],
            "fetched": false
        },
        "events": []
    },
    {
        "fixture": {
            "id": 1491960,
            "referee": null,
            "timezone": "America/New_York",
            "date": "2026-03-12T18:15:00-04:00",
            "timestamp": 1773353700,
            "periods": {
                "first": null,
                "second": null
            },
            "venue": {
                "id": null,
                "name": null,
                "city": "Cordoba"
            },
            "status": {
                "long": "Not Started",
                "short": "NS",
                "elapsed": null,
                "extra": null
            }
        },
        "league": {
            "id": 128,
            "name": "Liga Profesional Argentina",
            "country": "Argentina",
            "logo": "https://media.api-sports.io/football/leagues/128.png",
            "flag": "https://media.api-sports.io/flags/ar.svg",
            "season": 2026,
            "round": "Regular Season - 10",
            "standings": true
        },
        "teams": {
            "home": {
                "id": 2424,
                "name": "Estudiantes de Rio Cuarto",
                "logo": "https://media.api-sports.io/football/teams/2424.png",
                "winner": null,
                "rank": null,
                "record": null
            },
            "away": {
                "id": 440,
                "name": "Belgrano Cordoba",
                "logo": "https://media.api-sports.io/football/teams/440.png",
                "winner": null,
                "rank": null,
                "record": null
            }
        },
        "goals": {
            "home": null,
            "away": null
        },
        "homeLineup": null,
        "awayLineup": null,
        "odds": {
            "home": "TBD",
            "draw": "TBD",
            "away": "TBD",
            "total": "TBD",
            "over": "TBD",
            "under": "TBD"
        },
        "last_odds_check": null,
        "injuries": {
            "home": [],
            "away": [],
            "fetched": false
        },
        "events": []
    },
    {
        "fixture": {
            "id": 1491966,
            "referee": null,
            "timezone": "America/New_York",
            "date": "2026-03-12T18:15:00-04:00",
            "timestamp": 1773353700,
            "periods": {
                "first": null,
                "second": null
            },
            "venue": {
                "id": null,
                "name": "Estadio Mario Alberto Kempes",
                "city": "Cordoba"
            },
            "status": {
                "long": "Not Started",
                "short": "NS",
                "elapsed": null,
                "extra": null
            }
        },
        "league": {
            "id": 128,
            "name": "Liga Profesional Argentina",
            "country": "Argentina",
            "logo": "https://media.api-sports.io/football/leagues/128.png",
            "flag": "https://media.api-sports.io/flags/ar.svg",
            "season": 2026,
            "round": "Regular Season - 10",
            "standings": true
        },
        "teams": {
            "home": {
                "id": 456,
                "name": "Talleres Cordoba",
                "logo": "https://media.api-sports.io/football/teams/456.png",
                "winner": null,
                "rank": null,
                "record": null
            },
            "away": {
                "id": 478,
                "name": "Instituto Cordoba",
                "logo": "https://media.api-sports.io/football/teams/478.png",
                "winner": null,
                "rank": null,
                "record": null
            }
        },
        "goals": {
            "home": null,
            "away": null
        },
        "homeLineup": null,
        "awayLineup": null,
        "odds": {
            "home": "TBD",
            "draw": "TBD",
            "away": "TBD",
            "total": "TBD",
            "over": "TBD",
            "under": "TBD"
        },
        "last_odds_check": null,
        "injuries": {
            "home": [],
            "away": [],
            "fetched": false
        },
        "events": []
    },
    {
        "fixture": {
            "id": 1492159,
            "referee": null,
            "timezone": "America/New_York",
            "date": "2026-03-12T18:30:00-04:00",
            "timestamp": 1773354600,
            "periods": {
                "first": null,
                "second": null
            },
            "venue": {
                "id": null,
                "name": null,
                "city": "Rio de Janeiro"
            },
            "status": {
                "long": "Not Started",
                "short": "NS",
                "elapsed": null,
                "extra": null
            }
        },
        "league": {
            "id": 71,
            "name": "Serie A",
            "country": "Brazil",
            "logo": "https://media.api-sports.io/football/leagues/71.png",
            "flag": "https://media.api-sports.io/flags/br.svg",
            "season": 2026,
            "round": "Regular Season - 5",
            "standings": true
        },
        "teams": {
            "home": {
                "id": 133,
                "name": "Vasco DA Gama",
                "logo": "https://media.api-sports.io/football/teams/133.png",
                "winner": null,
                "rank": null,
                "record": null
            },
            "away": {
                "id": 121,
                "name": "Palmeiras",
                "logo": "https://media.api-sports.io/football/teams/121.png",
                "winner": null,
                "rank": null,
                "record": null
            }
        },
        "goals": {
            "home": null,
            "away": null
        },
        "homeLineup": null,
        "awayLineup": null,
        "odds": {
            "home": "TBD",
            "draw": "TBD",
            "away": "TBD",
            "total": "TBD",
            "over": "TBD",
            "under": "TBD"
        },
        "last_odds_check": null,
        "injuries": {
            "home": [],
            "away": [],
            "fetched": false
        },
        "events": []
    },
    {
        "fixture": {
            "id": 1492158,
            "referee": null,
            "timezone": "America/New_York",
            "date": "2026-03-12T19:00:00-04:00",
            "timestamp": 1773356400,
            "periods": {
                "first": null,
                "second": null
            },
            "venue": {
                "id": null,
                "name": "Estadio Do MorumBIS",
                "city": "Sao Paulo"
            },
            "status": {
                "long": "Not Started",
                "short": "NS",
                "elapsed": null,
                "extra": null
            }
        },
        "league": {
            "id": 71,
            "name": "Serie A",
            "country": "Brazil",
            "logo": "https://media.api-sports.io/football/leagues/71.png",
            "flag": "https://media.api-sports.io/flags/br.svg",
            "season": 2026,
            "round": "Regular Season - 5",
            "standings": true
        },
        "teams": {
            "home": {
                "id": 126,
                "name": "Sao Paulo",
                "logo": "https://media.api-sports.io/football/teams/126.png",
                "winner": null,
                "rank": null,
                "record": null
            },
            "away": {
                "id": 132,
                "name": "Chapecoense-sc",
                "logo": "https://media.api-sports.io/football/teams/132.png",
                "winner": null,
                "rank": null,
                "record": null
            }
        },
        "goals": {
            "home": null,
            "away": null
        },
        "homeLineup": null,
        "awayLineup": null,
        "odds": {
            "home": "TBD",
            "draw": "TBD",
            "away": "TBD",
            "total": "TBD",
            "over": "TBD",
            "under": "TBD"
        },
        "last_odds_check": null,
        "injuries": {
            "home": [],
            "away": [],
            "fetched": false
        },
        "events": []
    },
    {
        "fixture": {
            "id": 1491961,
            "referee": null,
            "timezone": "America/New_York",
            "date": "2026-03-12T20:30:00-04:00",
            "timestamp": 1773361800,
            "periods": {
                "first": null,
                "second": null
            },
            "venue": {
                "id": null,
                "name": null,
                "city": "Buenos Aires"
            },
            "status": {
                "long": "Not Started",
                "short": "NS",
                "elapsed": null,
                "extra": null
            }
        },
        "league": {
            "id": 128,
            "name": "Liga Profesional Argentina",
            "country": "Argentina",
            "logo": "https://media.api-sports.io/football/leagues/128.png",
            "flag": "https://media.api-sports.io/flags/ar.svg",
            "season": 2026,
            "round": "Regular Season - 10",
            "standings": true
        },
        "teams": {
            "home": {
                "id": 445,
                "name": "Huracan",
                "logo": "https://media.api-sports.io/football/teams/445.png",
                "winner": null,
                "rank": null,
                "record": null
            },
            "away": {
                "id": 435,
                "name": "River Plate",
                "logo": "https://media.api-sports.io/football/teams/435.png",
                "winner": null,
                "rank": null,
                "record": null
            }
        },
        "goals": {
            "home": null,
            "away": null
        },
        "homeLineup": null,
        "awayLineup": null,
        "odds": {
            "home": "TBD",
            "draw": "TBD",
            "away": "TBD",
            "total": "TBD",
            "over": "TBD",
            "under": "TBD"
        },
        "last_odds_check": null,
        "injuries": {
            "home": [],
            "away": [],
            "fetched": false
        },
        "events": []
    },
    {
        "fixture": {
            "id": 1492155,
            "referee": null,
            "timezone": "America/New_York",
            "date": "2026-03-12T20:30:00-04:00",
            "timestamp": 1773361800,
            "periods": {
                "first": null,
                "second": null
            },
            "venue": {
                "id": null,
                "name": null,
                "city": "Porto Alegre"
            },
            "status": {
                "long": "Not Started",
                "short": "NS",
                "elapsed": null,
                "extra": null
            }
        },
        "league": {
            "id": 71,
            "name": "Serie A",
            "country": "Brazil",
            "logo": "https://media.api-sports.io/football/leagues/71.png",
            "flag": "https://media.api-sports.io/flags/br.svg",
            "season": 2026,
            "round": "Regular Season - 5",
            "standings": true
        },
        "teams": {
            "home": {
                "id": 130,
                "name": "Gremio",
                "logo": "https://media.api-sports.io/football/teams/130.png",
                "winner": null,
                "rank": null,
                "record": null
            },
            "away": {
                "id": 794,
                "name": "RB Bragantino",
                "logo": "https://media.api-sports.io/football/teams/794.png",
                "winner": null,
                "rank": null,
                "record": null
            }
        },
        "goals": {
            "home": null,
            "away": null
        },
        "homeLineup": null,
        "awayLineup": null,
        "odds": {
            "home": "TBD",
            "draw": "TBD",
            "away": "TBD",
            "total": "TBD",
            "over": "TBD",
            "under": "TBD"
        },
        "last_odds_check": null,
        "injuries": {
            "home": [],
            "away": [],
            "fetched": false
        },
        "events": []
    },
    {
        "fixture": {
            "id": 1528291,
            "referee": null,
            "timezone": "America/New_York",
            "date": "2026-03-12T20:30:00-04:00",
            "timestamp": 1773361800,
            "periods": {
                "first": null,
                "second": null
            },
            "venue": {
                "id": null,
                "name": "Estadio Atanasio Girardot",
                "city": null
            },
            "status": {
                "long": "Not Started",
                "short": "NS",
                "elapsed": null,
                "extra": null
            }
        },
        "league": {
            "id": 13,
            "name": "CONMEBOL Libertadores",
            "country": "World",
            "logo": "https://media.api-sports.io/football/leagues/13.png",
            "flag": null,
            "season": 2026,
            "round": "Final",
            "standings": false
        },
        "teams": {
            "home": {
                "id": 1128,
                "name": "Independiente Medellin",
                "logo": "https://media.api-sports.io/football/teams/1128.png",
                "winner": null,
                "rank": null,
                "record": null
            },
            "away": {
                "id": 2353,
                "name": "Juventud",
                "logo": "https://media.api-sports.io/football/teams/2353.png",
                "winner": null,
                "rank": null,
                "record": null
            }
        },
        "goals": {
            "home": null,
            "away": null
        },
        "homeLineup": null,
        "awayLineup": null,
        "odds": {
            "home": "TBD",
            "draw": "TBD",
            "away": "TBD",
            "total": "TBD",
            "over": "TBD",
            "under": "TBD"
        },
        "last_odds_check": null,
        "injuries": {
            "home": [],
            "away": [],
            "fetched": false
        },
        "events": []
    }
]